README.txt
setup.py
calculator/Calculator.py
calculator/__init__.py
calculator/calculator.py
justinascalculator.egg-info/PKG-INFO
justinascalculator.egg-info/SOURCES.txt
justinascalculator.egg-info/dependency_links.txt
justinascalculator.egg-info/requires.txt
justinascalculator.egg-info/top_level.txt
test/__init__.py
test/test.py