Metadata-Version: 2.1
Name: justinascalculator
Version: 0.0.9
Summary: Simple calculator
Home-page: UNKNOWN
Author: Justinas Klevinskas
Author-email: justinas@klevinskas.lt
License: UNKNOWN
Platform: UNKNOWN
Classifier: Programming Language :: Python :: 3
Classifier: License :: OSI Approved :: MIT License
Classifier: Operating System :: OS Independent
Requires-Python: >=3.6
